holmes/__init__.py
holmes/__main__.py
holmes/app.py
holmes/config.py
holmes/data.py
holmes/exceptions.py
holmes/logging.py
holmes/validation.py
holmes/api/__init__.py
holmes/api/api.py
holmes/api/calibration.py
holmes/api/projection.py
holmes/api/simulation.py
holmes/api/utils.py
holmes/data/Au Saumon_CemaNeigeInfo.csv
holmes/data/Au Saumon_Observations.csv
holmes/data/Au Saumon_Projections.csv
holmes/data/Baskatong_CemaNeigeInfo.csv
holmes/data/Baskatong_Observations.csv
holmes/data/Baskatong_Projections.csv
holmes/data/Leaf_Observations.csv
holmes/models/__init__.py
holmes/models/calibration.py
holmes/models/hydro.py
holmes/models/snow.py
holmes/models/utils.py
holmes/static/index.html
holmes/static/assets/icons/favicon.svg
holmes/static/assets/icons/icons.svg
holmes/static/assets/icons/loading.svg
holmes/static/scripts/calibration.js
holmes/static/scripts/index.js
holmes/static/scripts/nav.js
holmes/static/scripts/notifications.js
holmes/static/scripts/projection.js
holmes/static/scripts/settings.js
holmes/static/scripts/simulation.js
holmes/static/scripts/libraries/d3.js
holmes/static/scripts/libraries/d3.v7.min.js
holmes/static/scripts/utils/elements.js
holmes/static/scripts/utils/listeners.js
holmes/static/scripts/utils/misc.js
holmes/static/scripts/utils/ws.js
holmes/static/styles/calibration.css
holmes/static/styles/elements.css
holmes/static/styles/index.css
holmes/static/styles/nav.css
holmes/static/styles/notifications.css
holmes/static/styles/projection.css
holmes/static/styles/settings.css
holmes/static/styles/simulation.css
holmes/static/styles/template.css
holmes/utils/__init__.py
holmes/utils/paths.py
holmes/utils/print.py
holmes/utils/websocket.py
holmes_hydro-3.4.0.dist-info/METADATA
holmes_hydro-3.4.0.dist-info/WHEEL
holmes_hydro-3.4.0.dist-info/entry_points.txt
holmes_hydro-3.4.0.dist-info/licenses/LICENSE
holmes_hydro-3.4.0.dist-info/RECORD
