Metadata-Version: 2.4
Name: holmes-hydro
Version: 3.4.0
Summary: HOLMES (HydrOLogical Modeling Educationnal Software) is a software developped to teach operational hydrology. It is developed at the university Laval, Québec, Canada.
Project-URL: Homepage, https://github.com/antoinelb/holmes
Project-URL: Repository, https://github.com/antoinelb/holmes
Author-email: Antoine Lefebvre-Brossard <antoinelb@proton.me>
License: MIT
License-File: LICENSE
Classifier: Development Status :: 3 - Alpha
Classifier: Intended Audience :: Education
Classifier: Operating System :: OS Independent
Classifier: Programming Language :: Python :: 3
Classifier: Programming Language :: Python :: 3.11
Classifier: Programming Language :: Python :: 3.12
Classifier: Programming Language :: Python :: 3.13
Classifier: Topic :: Scientific/Engineering :: Hydrology
Requires-Python: >=3.11
Requires-Dist: holmes-rs>=0.3.0
Requires-Dist: numpy>=2.4.0
Requires-Dist: polars>=1.36.0
Requires-Dist: starlette>=0.50.0
Requires-Dist: uvicorn>=0.36.0
Requires-Dist: websockets>=15.0.1
